<?xml version="1.0" encoding="ISO-8859-1" ?>
<ans:mensagemTISS xmlns="http://www.w3.org/2001/XMLSchema" xmlns:ans="http://www.ans.gov.br/padroes/tiss/schemas">
<ans:cabecalho>
<ans:identificacaoTransacao>
<ans:tipoTransacao>ENVIO_LOTE_GUIAS</ans:tipoTransacao>
<ans:sequencialTransacao>1</ans:sequencialTransacao>
<ans:dataRegistroTransacao>29/05/2008</ans:dataRegistroTransacao>
<ans:horaRegistroTransacao>15:49</ans:horaRegistroTransacao>
</ans:identificacaoTransacao>
<ans:origem>
<ans:codigoPrestadorNaOperadora>
<ans:CNPJ>02762719000195</ans:CNPJ>
</ans:codigoPrestadorNaOperadora>
</ans:origem>
<ans:destino>
<ans:registroANS>0</ans:registroANS>
</ans:destino>
<ans:versaoPadrao>2.01.03</ans:versaoPadrao>
</ans:cabecalho>
<ans:prestadorParaOperadora>
<ans:loteGuias>
<ans:numeroLote>1545</ans:numeroLote>
<ans:guias>
<ans:guiaFaturamento>
<ans:guiaConsulta>
<ans:identificacaoGuia>
<ans:registroANS>0</ans:registroANS>
<ans:dataEmissaoGuia>29/05/2008</ans:dataEmissaoGuia>
<ans:numeroGuiaPrestador>1</ans:numeroGuiaPrestador>
<ans:numeroGuiaOperadora>1</ans:numeroGuiaOperadora>
</ans:identificacaoGuia>
<ans:beneficiario>
<ans:numeroCarteira>548787</ans:numeroCarteira>
<ans:nomeBeneficiario>Fabiano de Oliveira Prado</ans:nomeBeneficiario>
<ans:nomePlano>PLANO DE SAUDE 1</ans:nomePlano>
<ans:validadeCarteira>28/06/2008</ans:validadeCarteira>
<ans:numeroCNS>45787</ans:numeroCNS>
</ans:beneficiario>
<ans:dadosContratado>
<ans:identificacao>
<ans:CNPJ>02762719000195</ans:CNPJ>
</ans:identificacao>
<ans:nomeContratado>CLÍNICA</ans:nomeContratado>
<ans:enderecoContratado>
<ans:tipoLogradouro>008</ans:tipoLogradouro>
<ans:logradouro>Av. dos Anjos</ans:logradouro>
<ans:numero>457</ans:numero>
<ans:complemento>Complemento</ans:complemento>
<ans:codigoIBGEMunicipio>0000014</ans:codigoIBGEMunicipio>
<ans:municipio>Itaperuna</ans:municipio>
<ans:codigoUF>RJ</ans:codigoUF>
<ans:cep>28380000</ans:cep>
</ans:enderecoContratado>
<ans:numeroCNES>0000457</ans:numeroCNES>
</ans:dadosContratado>
<ans:profissionalExecutante>
<ans:nomeProfissional>Médico</ans:nomeProfissional>
<ans:conselhoProfissional>
<ans:siglaConselho>CRM</ans:siglaConselho>
<ans:numeroConselho>02457</ans:numeroConselho>
<ans:ufConselho>RJ</ans:ufConselho>
</ans:conselhoProfissional>
<ans:cbos>01280</ans:cbos>
</ans:profissionalExecutante>
<ans:hipoteseDiagnostica>
<ans:CID>
<ans:nomeTabela>CID-10</ans:nomeTabela>
<ans:codigoDiagnostico></ans:codigoDiagnostico>
<ans:descricaoDiagnostico></ans:descricaoDiagnostico>
</ans:CID>
<ans:tipoDoenca>A</ans:tipoDoenca>
<ans:tempoReferidoEvolucaoDoenca>
<ans:valor>10</ans:valor>
<ans:unidadeTempo>D</ans:unidadeTempo>
</ans:tempoReferidoEvolucaoDoenca>
<ans:indicadorAcidente>1</ans:indicadorAcidente>
</ans:hipoteseDiagnostica>
<ans:dadosAtendimento>
<ans:dataAtendimento>30/12/1899</ans:dataAtendimento>
<ans:procedimento>
<ans:codigoTabela>01</ans:codigoTabela>
<ans:codigoProcedimento>00010014</ans:codigoProcedimento>
</ans:procedimento>
<ans:tipoConsulta>1</ans:tipoConsulta>
<ans:tipoSaida>5</ans:tipoSaida>
</ans:dadosAtendimento>
<ans:observacao>OBSERVAÇÕES SOBRE A CONSULTA</ans:observacao>
</ans:guiaConsulta>
<ans:guiaConsulta>
<ans:identificacaoGuia>
<ans:registroANS>0</ans:registroANS>
<ans:dataEmissaoGuia>29/05/2008</ans:dataEmissaoGuia>
<ans:numeroGuiaPrestador>2</ans:numeroGuiaPrestador>
<ans:numeroGuiaOperadora>2</ans:numeroGuiaOperadora>
</ans:identificacaoGuia>
<ans:beneficiario>
<ans:numeroCarteira>548787</ans:numeroCarteira>
<ans:nomeBeneficiario>Fabiano de Oliveira Prado</ans:nomeBeneficiario>
<ans:nomePlano>PLANO DE SAUDE 2</ans:nomePlano>
<ans:validadeCarteira>28/06/2008</ans:validadeCarteira>
<ans:numeroCNS>45787</ans:numeroCNS>
</ans:beneficiario>
<ans:dadosContratado>
<ans:identificacao>
<ans:CNPJ>02762719000195</ans:CNPJ>
</ans:identificacao>
<ans:nomeContratado>CLÍNICA</ans:nomeContratado>
<ans:enderecoContratado>
<ans:tipoLogradouro>008</ans:tipoLogradouro>
<ans:logradouro>Av. dos Anjos</ans:logradouro>
<ans:numero>457</ans:numero>
<ans:complemento>Complemento</ans:complemento>
<ans:codigoIBGEMunicipio>0000014</ans:codigoIBGEMunicipio>
<ans:municipio>Itaperuna</ans:municipio>
<ans:codigoUF>RJ</ans:codigoUF>
<ans:cep>28380000</ans:cep>
</ans:enderecoContratado>
<ans:numeroCNES>0000457</ans:numeroCNES>
</ans:dadosContratado>
<ans:profissionalExecutante>
<ans:nomeProfissional>Médico</ans:nomeProfissional>
<ans:conselhoProfissional>
<ans:siglaConselho>CRM</ans:siglaConselho>
<ans:numeroConselho>02457</ans:numeroConselho>
<ans:ufConselho>RJ</ans:ufConselho>
</ans:conselhoProfissional>
<ans:cbos>01280</ans:cbos>
</ans:profissionalExecutante>
<ans:hipoteseDiagnostica>
<ans:CID>
<ans:nomeTabela>CID-10</ans:nomeTabela>
<ans:codigoDiagnostico></ans:codigoDiagnostico>
<ans:descricaoDiagnostico></ans:descricaoDiagnostico>
</ans:CID>
<ans:tipoDoenca>A</ans:tipoDoenca>
<ans:tempoReferidoEvolucaoDoenca>
<ans:valor>10</ans:valor>
<ans:unidadeTempo>D</ans:unidadeTempo>
</ans:tempoReferidoEvolucaoDoenca>
<ans:indicadorAcidente>1</ans:indicadorAcidente>
</ans:hipoteseDiagnostica>
<ans:dadosAtendimento>
<ans:dataAtendimento>30/12/1899</ans:dataAtendimento>
<ans:procedimento>
<ans:codigoTabela>01</ans:codigoTabela>
<ans:codigoProcedimento>00010014</ans:codigoProcedimento>
</ans:procedimento>
<ans:tipoConsulta>1</ans:tipoConsulta>
<ans:tipoSaida>5</ans:tipoSaida>
</ans:dadosAtendimento>
<ans:observacao>OBSERVAÇÕES SOBRE A CONSULTA</ans:observacao>
</ans:guiaConsulta>
<ans:guiaConsulta>
<ans:identificacaoGuia>
<ans:registroANS>0</ans:registroANS>
<ans:dataEmissaoGuia>29/05/2008</ans:dataEmissaoGuia>
<ans:numeroGuiaPrestador>3</ans:numeroGuiaPrestador>
<ans:numeroGuiaOperadora>3</ans:numeroGuiaOperadora>
</ans:identificacaoGuia>
<ans:beneficiario>
<ans:numeroCarteira>548787</ans:numeroCarteira>
<ans:nomeBeneficiario>Fabiano de Oliveira Prado</ans:nomeBeneficiario>
<ans:nomePlano>PLANO DE SAUDE 3</ans:nomePlano>
<ans:validadeCarteira>28/06/2008</ans:validadeCarteira>
<ans:numeroCNS>45787</ans:numeroCNS>
</ans:beneficiario>
<ans:dadosContratado>
<ans:identificacao>
<ans:CNPJ>02762719000195</ans:CNPJ>
</ans:identificacao>
<ans:nomeContratado>CLÍNICA</ans:nomeContratado>
<ans:enderecoContratado>
<ans:tipoLogradouro>008</ans:tipoLogradouro>
<ans:logradouro>Av. dos Anjos</ans:logradouro>
<ans:numero>457</ans:numero>
<ans:complemento>Complemento</ans:complemento>
<ans:codigoIBGEMunicipio>0000014</ans:codigoIBGEMunicipio>
<ans:municipio>Itaperuna</ans:municipio>
<ans:codigoUF>RJ</ans:codigoUF>
<ans:cep>28380000</ans:cep>
</ans:enderecoContratado>
<ans:numeroCNES>0000457</ans:numeroCNES>
</ans:dadosContratado>
<ans:profissionalExecutante>
<ans:nomeProfissional>Médico</ans:nomeProfissional>
<ans:conselhoProfissional>
<ans:siglaConselho>CRM</ans:siglaConselho>
<ans:numeroConselho>02457</ans:numeroConselho>
<ans:ufConselho>RJ</ans:ufConselho>
</ans:conselhoProfissional>
<ans:cbos>01280</ans:cbos>
</ans:profissionalExecutante>
<ans:hipoteseDiagnostica>
<ans:CID>
<ans:nomeTabela>CID-10</ans:nomeTabela>
<ans:codigoDiagnostico></ans:codigoDiagnostico>
<ans:descricaoDiagnostico></ans:descricaoDiagnostico>
</ans:CID>
<ans:tipoDoenca>A</ans:tipoDoenca>
<ans:tempoReferidoEvolucaoDoenca>
<ans:valor>10</ans:valor>
<ans:unidadeTempo>D</ans:unidadeTempo>
</ans:tempoReferidoEvolucaoDoenca>
<ans:indicadorAcidente>1</ans:indicadorAcidente>
</ans:hipoteseDiagnostica>
<ans:dadosAtendimento>
<ans:dataAtendimento>30/12/1899</ans:dataAtendimento>
<ans:procedimento>
<ans:codigoTabela>01</ans:codigoTabela>
<ans:codigoProcedimento>00010014</ans:codigoProcedimento>
</ans:procedimento>
<ans:tipoConsulta>1</ans:tipoConsulta>
<ans:tipoSaida>5</ans:tipoSaida>
</ans:dadosAtendimento>
<ans:observacao>OBSERVAÇÕES SOBRE A CONSULTA</ans:observacao>
</ans:guiaConsulta>
<ans:guiaConsulta>
<ans:identificacaoGuia>
<ans:registroANS>0</ans:registroANS>
<ans:dataEmissaoGuia>29/05/2008</ans:dataEmissaoGuia>
<ans:numeroGuiaPrestador>4</ans:numeroGuiaPrestador>
<ans:numeroGuiaOperadora>4</ans:numeroGuiaOperadora>
</ans:identificacaoGuia>
<ans:beneficiario>
<ans:numeroCarteira>548787</ans:numeroCarteira>
<ans:nomeBeneficiario>Fabiano de Oliveira Prado</ans:nomeBeneficiario>
<ans:nomePlano>PLANO DE SAUDE 4</ans:nomePlano>
<ans:validadeCarteira>28/06/2008</ans:validadeCarteira>
<ans:numeroCNS>45787</ans:numeroCNS>
</ans:beneficiario>
<ans:dadosContratado>
<ans:identificacao>
<ans:CNPJ>02762719000195</ans:CNPJ>
</ans:identificacao>
<ans:nomeContratado>CLÍNICA</ans:nomeContratado>
<ans:enderecoContratado>
<ans:tipoLogradouro>008</ans:tipoLogradouro>
<ans:logradouro>Av. dos Anjos</ans:logradouro>
<ans:numero>457</ans:numero>
<ans:complemento>Complemento</ans:complemento>
<ans:codigoIBGEMunicipio>0000014</ans:codigoIBGEMunicipio>
<ans:municipio>Itaperuna</ans:municipio>
<ans:codigoUF>RJ</ans:codigoUF>
<ans:cep>28380000</ans:cep>
</ans:enderecoContratado>
<ans:numeroCNES>0000457</ans:numeroCNES>
</ans:dadosContratado>
<ans:profissionalExecutante>
<ans:nomeProfissional>Médico</ans:nomeProfissional>
<ans:conselhoProfissional>
<ans:siglaConselho>CRM</ans:siglaConselho>
<ans:numeroConselho>02457</ans:numeroConselho>
<ans:ufConselho>RJ</ans:ufConselho>
</ans:conselhoProfissional>
<ans:cbos>01280</ans:cbos>
</ans:profissionalExecutante>
<ans:hipoteseDiagnostica>
<ans:CID>
<ans:nomeTabela>CID-10</ans:nomeTabela>
<ans:codigoDiagnostico></ans:codigoDiagnostico>
<ans:descricaoDiagnostico></ans:descricaoDiagnostico>
</ans:CID>
<ans:tipoDoenca>A</ans:tipoDoenca>
<ans:tempoReferidoEvolucaoDoenca>
<ans:valor>10</ans:valor>
<ans:unidadeTempo>D</ans:unidadeTempo>
</ans:tempoReferidoEvolucaoDoenca>
<ans:indicadorAcidente>1</ans:indicadorAcidente>
</ans:hipoteseDiagnostica>
<ans:dadosAtendimento>
<ans:dataAtendimento>30/12/1899</ans:dataAtendimento>
<ans:procedimento>
<ans:codigoTabela>01</ans:codigoTabela>
<ans:codigoProcedimento>00010014</ans:codigoProcedimento>
</ans:procedimento>
<ans:tipoConsulta>1</ans:tipoConsulta>
<ans:tipoSaida>5</ans:tipoSaida>
</ans:dadosAtendimento>
<ans:observacao>OBSERVAÇÕES SOBRE A CONSULTA</ans:observacao>
</ans:guiaConsulta>
<ans:guiaConsulta>
<ans:identificacaoGuia>
<ans:registroANS>0</ans:registroANS>
<ans:dataEmissaoGuia>29/05/2008</ans:dataEmissaoGuia>
<ans:numeroGuiaPrestador>5</ans:numeroGuiaPrestador>
<ans:numeroGuiaOperadora>5</ans:numeroGuiaOperadora>
</ans:identificacaoGuia>
<ans:beneficiario>
<ans:numeroCarteira>548787</ans:numeroCarteira>
<ans:nomeBeneficiario>Fabiano de Oliveira Prado</ans:nomeBeneficiario>
<ans:nomePlano>PLANO DE SAUDE 5</ans:nomePlano>
<ans:validadeCarteira>28/06/2008</ans:validadeCarteira>
<ans:numeroCNS>45787</ans:numeroCNS>
</ans:beneficiario>
<ans:dadosContratado>
<ans:identificacao>
<ans:CNPJ>02762719000195</ans:CNPJ>
</ans:identificacao>
<ans:nomeContratado>CLÍNICA</ans:nomeContratado>
<ans:enderecoContratado>
<ans:tipoLogradouro>008</ans:tipoLogradouro>
<ans:logradouro>Av. dos Anjos</ans:logradouro>
<ans:numero>457</ans:numero>
<ans:complemento>Complemento</ans:complemento>
<ans:codigoIBGEMunicipio>0000014</ans:codigoIBGEMunicipio>
<ans:municipio>Itaperuna</ans:municipio>
<ans:codigoUF>RJ</ans:codigoUF>
<ans:cep>28380000</ans:cep>
</ans:enderecoContratado>
<ans:numeroCNES>0000457</ans:numeroCNES>
</ans:dadosContratado>
<ans:profissionalExecutante>
<ans:nomeProfissional>Médico</ans:nomeProfissional>
<ans:conselhoProfissional>
<ans:siglaConselho>CRM</ans:siglaConselho>
<ans:numeroConselho>02457</ans:numeroConselho>
<ans:ufConselho>RJ</ans:ufConselho>
</ans:conselhoProfissional>
<ans:cbos>01280</ans:cbos>
</ans:profissionalExecutante>
<ans:hipoteseDiagnostica>
<ans:CID>
<ans:nomeTabela>CID-10</ans:nomeTabela>
<ans:codigoDiagnostico></ans:codigoDiagnostico>
<ans:descricaoDiagnostico></ans:descricaoDiagnostico>
</ans:CID>
<ans:tipoDoenca>A</ans:tipoDoenca>
<ans:tempoReferidoEvolucaoDoenca>
<ans:valor>10</ans:valor>
<ans:unidadeTempo>D</ans:unidadeTempo>
</ans:tempoReferidoEvolucaoDoenca>
<ans:indicadorAcidente>1</ans:indicadorAcidente>
</ans:hipoteseDiagnostica>
<ans:dadosAtendimento>
<ans:dataAtendimento>30/12/1899</ans:dataAtendimento>
<ans:procedimento>
<ans:codigoTabela>01</ans:codigoTabela>
<ans:codigoProcedimento>00010014</ans:codigoProcedimento>
</ans:procedimento>
<ans:tipoConsulta>1</ans:tipoConsulta>
<ans:tipoSaida>5</ans:tipoSaida>
</ans:dadosAtendimento>
<ans:observacao>OBSERVAÇÕES SOBRE A CONSULTA</ans:observacao>
</ans:guiaConsulta>
</ans:guiaFaturamento>
</ans:guias>
</ans:loteGuias>
</ans:prestadorParaOperadora>
<ans:epilogo>
<ans:hash>fb437d6aedd0fdbe44160ffcfbdc7235</ans:hash>
</ans:epilogo>
</ans:mensagemTISS>
